setup.py
jsonrpcparts/__init__.py
jsonrpcparts/application.py
jsonrpcparts/client.py
jsonrpcparts/errors.py
jsonrpcparts/serializers.py
jsonrpcparts/wsgiapplication.py
jsonrpcparts.egg-info/PKG-INFO
jsonrpcparts.egg-info/SOURCES.txt
jsonrpcparts.egg-info/dependency_links.txt
jsonrpcparts.egg-info/requires.txt
jsonrpcparts.egg-info/top_level.txt