Metadata-Version: 1.1
Name: jsonrpcparts
Version: 0.3.3
Summary: JSON-RPC client and server components
Home-page: http://github.com/dvdotsenko/jsonrpc.py
Author: Daniel Dotsenko
Author-email: dotsa@hotmail.com
License: MIT
Download-URL: http://github.com/dvdotsenko/jsonrpc.py/tarball/master
Keywords: JSON,jsonrpc,rpc,wsgi
Platform: UNKNOWN
Classifier: Development Status :: 4 - Beta
Classifier: Environment :: Web Environment
Classifier: Intended Audience :: Developers
Classifier: License :: OSI Approved :: MIT License
Classifier: Operating System :: OS Independent
Classifier: Programming Language :: Python :: 2.6
Classifier: Programming Language :: Python :: 2.7
Classifier: Topic :: Internet
Classifier: Topic :: Internet :: WWW/HTTP
Classifier: Topic :: Internet :: WWW/HTTP :: WSGI
Classifier: Topic :: Internet :: WWW/HTTP :: WSGI :: Application
